my_pm10_predictor/__init__.py
my_pm10_predictor/data_loader.py
my_pm10_predictor/model_loader.py
my_pm10_predictor/predictor.py
my_pm10_predictor/utils.py
my_pm10_predictor/visualizer.py
pm10_data_cleaning/__init__.py
pm10_data_cleaning/data_cleaner.py
pm10_data_cleaning/run_data_cleaning.py
my_pm10_prediction-0.2.0.dist-info/METADATA
my_pm10_prediction-0.2.0.dist-info/WHEEL
my_pm10_prediction-0.2.0.dist-info/top_level.txt
my_pm10_prediction-0.2.0.dist-info/RECORD
