Metadata-Version: 2.1
Name: my-pm10-prediction
Version: 0.2.0
Summary: A package for PM10 air quality prediction and data cleaning
Home-page: https://github.com/yourusername/my_pm10_prediction
Author: Your Name
Author-email: your.email@example.com
Classifier: Programming Language :: Python :: 3
Classifier: License :: OSI Approved :: MIT License
Classifier: Operating System :: OS Independent
Requires-Python: >=3.6
Requires-Dist: pandas
Requires-Dist: numpy
Requires-Dist: scikit-learn
Requires-Dist: seaborn
Requires-Dist: matplotlib
Requires-Dist: keras
Requires-Dist: joblib
